{
  "content": [
    {
      "content": null,
      "created": "2022-07-30T22:24:04.073159Z",
      "format": null,
      "last_modified": "2022-07-30T22:24:04.073159Z",
      "mimetype": null,
      "name": "data",
      "path": "data",
      "size": null,
      "type": "directory",
      "writable": true
    },
    {
      "content": null,
      "created": "2022-07-30T22:24:04.073159Z",
      "format": null,
      "last_modified": "2022-07-30T22:23:08.921645Z",
      "mimetype": null,
      "name": "example_workflow_ronaldo.ipynb",
      "path": "example_workflow_ronaldo.ipynb",
      "size": 4796,
      "type": "notebook",
      "writable": true
    },
    {
      "content": null,
      "created": "2022-07-30T22:24:04.065159Z",
      "format": null,
      "last_modified": "2022-07-30T22:24:02.461168Z",
      "mimetype": "text/markdown",
      "name": "README.md",
      "path": "README.md",
      "size": 709,
      "type": "file",
      "writable": true
    }
  ],
  "created": "2022-07-30T22:24:04.073159Z",
  "format": "json",
  "last_modified": "2022-07-30T22:24:04.073159Z",
  "mimetype": null,
  "name": "",
  "path": "",
  "size": null,
  "type": "directory",
  "writable": true
}